django_variantmpl-0.1.0.dist-info/DESCRIPTION.rst
django_variantmpl-0.1.0.dist-info/METADATA
django_variantmpl-0.1.0.dist-info/RECORD
django_variantmpl-0.1.0.dist-info/WHEEL
django_variantmpl-0.1.0.dist-info/metadata.json
django_variantmpl-0.1.0.dist-info/top_level.txt
variantmpl/__init__.py
variantmpl/conf.py
variantmpl/constants.py
variantmpl/decorators.py
variantmpl/monkey.py
variantmpl/shortcuts.py
