Metadata-Version: 2.0
Name: django-variantmpl
Version: 0.1.0
Summary: Provide a mechanism for Django that switching template based on request context.
Home-page: https://github.com/tell-k/django-variantmpl
Author: tell-k
Author-email: ffk2005@gmail.com
License: MIT
Keywords: django templates switch useragent
Platform: UNKNOWN
Classifier: Environment :: Web Environment
Classifier: Framework :: Django
Classifier: Intended Audience :: Developers
Classifier: License :: OSI Approved :: MIT License
Classifier: Operating System :: OS Independent
Classifier: Framework :: Django
Classifier: Framework :: Django :: 1.10
Classifier: Framework :: Django :: 1.11
Classifier: Framework :: Django :: 2.0
Classifier: Programming Language :: Python
Classifier: Programming Language :: Python :: 3
Classifier: Programming Language :: Python :: 3.4
Classifier: Programming Language :: Python :: 3.5
Classifier: Programming Language :: Python :: 3.6
Requires-Dist: Django
